pytorch_bench/__init__.py
pytorch_bench/main.py
pytorch_bench-0.1.4.dist-info/licenses/LICENSE
pytorch_bench-0.1.4.dist-info/METADATA
pytorch_bench-0.1.4.dist-info/WHEEL
pytorch_bench-0.1.4.dist-info/top_level.txt
pytorch_bench-0.1.4.dist-info/RECORD
