Metadata-Version: 2.4
Name: pytorch_bench
Version: 0.1.4
Summary: torch benchmarking tool
Home-page: https://github.com/MaximeGloesener/torch-benchmark
Author: Maxime Gloesener
Author-email: max.gleu@gmail.com
License-File: LICENSE
Requires-Dist: torch
Requires-Dist: pynvml
Requires-Dist: matplotlib
Requires-Dist: numpy
Requires-Dist: torchprofile
Requires-Dist: codecarbon
Dynamic: author
Dynamic: author-email
Dynamic: description
Dynamic: description-content-type
Dynamic: home-page
Dynamic: license-file
Dynamic: requires-dist
Dynamic: summary
